MANIFEST.in
requirements.txt
setup.py
suit_guardian/__init__.py
suit_guardian.egg-info/PKG-INFO
suit_guardian.egg-info/SOURCES.txt
suit_guardian.egg-info/dependency_links.txt
suit_guardian.egg-info/not-zip-safe
suit_guardian.egg-info/requires.txt
suit_guardian.egg-info/top_level.txt
suit_guardian/templates/admin/guardian/model/change_form.html
suit_guardian/templates/admin/guardian/model/field.html
suit_guardian/templates/admin/guardian/model/obj_perms_manage.html
suit_guardian/templates/admin/guardian/model/obj_perms_manage_group.html
suit_guardian/templates/admin/guardian/model/obj_perms_manage_user.html